MEAutility/__init__.py
MEAutility/core.py
MEAutility/plotting.py
MEAutility/electrodes/Neuronexus-32.yaml
MEAutility/electrodes/Neuropixels-128.yaml
MEAutility/electrodes/Neuropixels-24.yaml
MEAutility/electrodes/Neuropixels-384.yaml
MEAutility/electrodes/Neuropixels-64.yaml
MEAutility/electrodes/Neuropixels2-128.yaml
MEAutility/electrodes/Neuropixels2-24.yaml
MEAutility/electrodes/Neuropixels2-384.yaml
MEAutility/electrodes/Neuropixels2-64.yaml
MEAutility/electrodes/Neuroseeker-128.yaml
MEAutility/electrodes/SqMEA-10-15.yaml
MEAutility/electrodes/SqMEA-15-10.yaml
MEAutility/electrodes/SqMEA-5-30.yaml
MEAutility/electrodes/SqMEA-6-25.yaml
MEAutility/electrodes/SqMEA-7-20.yaml
MEAutility/electrodes/monotrode.yaml
MEAutility/electrodes/tetrode-mea-d.yaml
MEAutility/electrodes/tetrode-mea-l.yaml
MEAutility/electrodes/tetrode-mea-s.yaml
MEAutility/electrodes/tetrode.yaml
meautility-1.5.3.dist-info/licenses/LICENSE
meautility-1.5.3.dist-info/METADATA
meautility-1.5.3.dist-info/WHEEL
meautility-1.5.3.dist-info/top_level.txt
meautility-1.5.3.dist-info/RECORD
