Metadata-Version: 2.4
Name: MEAutility
Version: 1.5.3
Summary: Python package for multi-electrode array (MEA) handling and stimulation.
Author-email: Alessio Buccino <alessiop.buccino@gmail.com>
Project-URL: homepage, https://github.com/alejoe91/MEAutility
Project-URL: repository, https://github.com/alejoe91/MEAutility
Project-URL: documentation, https://meautility.readthedocs.io/en/latest/ 
Classifier: Programming Language :: Python :: 3
Classifier: License :: OSI Approved :: MIT License
Classifier: Operating System :: OS Independent
Requires-Python: >=3.8
License-File: LICENSE
Requires-Dist: numpy
Requires-Dist: pyyaml
Requires-Dist: matplotlib
Dynamic: license-file
